README.md
setup.py
./bin/semester-planner
semester_planner/__init__.py
semester_planner/config.py
semester_planner/data.py
semester_planner/utils.py
semester_planner.egg-info/PKG-INFO
semester_planner.egg-info/SOURCES.txt
semester_planner.egg-info/dependency_links.txt
semester_planner.egg-info/entry_points.txt
semester_planner.egg-info/not-zip-safe
semester_planner.egg-info/requires.txt
semester_planner.egg-info/top_level.txt
semester_planner/cli/__init__.py
semester_planner/cli/utils.py