Metadata-Version: 2.1
Name: semester-planner
Version: 1.2.0
Summary: Utility to plan your semester in different apps.
Home-page: https://github.com/VoIlAlex/semester-planner
Author: voilalex
Author-email: ilya.vouk@gmail.com
License: MIT
Download-URL: https://github.com/VoIlAlex/semester-planner/archive/v1.2.0.tar.gz
Keywords: utility,todoist,cli,planner,study
Platform: UNKNOWN
Classifier: Development Status :: 3 - Alpha
Classifier: Environment :: Console
Classifier: License :: OSI Approved :: MIT License
Classifier: Programming Language :: Python :: 3
Classifier: Programming Language :: Python :: 3.5
Classifier: Programming Language :: Python :: 3.6
Classifier: Programming Language :: Python :: 3.7
